django_app_router/__init__.py
django_app_router/routers.py
django_app_router/utils.py
django_app_router-0.1.1.dist-info/LICENSE
django_app_router-0.1.1.dist-info/METADATA
django_app_router-0.1.1.dist-info/WHEEL
django_app_router-0.1.1.dist-info/top_level.txt
django_app_router-0.1.1.dist-info/RECORD
