Metadata-Version: 2.1
Name: django-app-router
Version: 0.1.1
Summary: A simple Django app to route requests, Inspired by Next.js App Router.
Home-page: https://github.com/staciax/django-app-router
Author: STACiA
License: MIT
Project-URL: Issue tracker, https://github.com/staciax/django-app-router/issues
Classifier: License :: OSI Approved :: MIT License
Classifier: Intended Audience :: Developers
Classifier: Natural Language :: English
Classifier: Operating System :: OS Independent
Classifier: Programming Language :: Python :: 3
Classifier: Programming Language :: Python :: 3.8
Classifier: Programming Language :: Python :: 3.9
Classifier: Programming Language :: Python :: 3.10
Classifier: Programming Language :: Python :: 3.11
Classifier: Programming Language :: Python :: 3.12
Requires-Python: >=3.8.0
License-File: LICENSE
Requires-Dist: Django >=4.2.0
